fsxpathlib/__init__.py
fsxpathlib/_version.py
fsxpathlib/client.py
fsxpathlib/exc.py
fsxpathlib/hashes.py
fsxpathlib/helper.py
fsxpathlib/logger.py
fsxpathlib/path.py
fsxpathlib/tests/__init__.py
fsxpathlib/tests/log.txt
fsxpathlib/vendors/__init__.py
fsxpathlib/vendors/iterproxy.py
fsxpathlib-1.0.0.dist-info/AUTHORS.rst
fsxpathlib-1.0.0.dist-info/LICENSE
fsxpathlib-1.0.0.dist-info/METADATA
fsxpathlib-1.0.0.dist-info/NOTICE
fsxpathlib-1.0.0.dist-info/WHEEL
fsxpathlib-1.0.0.dist-info/top_level.txt
fsxpathlib-1.0.0.dist-info/RECORD
