Metadata-Version: 2.1
Name: fsxpathlib
Version: 1.0.0
Summary: Objective Oriented Interface for AWS FSx, similar to boto3 APIs for s3.
Download-URL: https://pypi.python.org/pypi/fsxpathlib/1.0.0#downloads
Author: Ivan Chen
Author-email: chen115yaohua@gmail.com
Classifier: Development Status :: 4 - Beta
Classifier: Intended Audience :: Developers
Classifier: License :: OSI Approved :: Apache Software License
Classifier: Natural Language :: English
Classifier: Operating System :: Microsoft :: Windows
Classifier: Operating System :: MacOS
Classifier: Operating System :: Unix
Classifier: Natural Language :: English
Classifier: Programming Language :: Python
Classifier: Programming Language :: Python :: 3 :: Only
Classifier: Programming Language :: Python :: 3.6
Classifier: Programming Language :: Python :: 3.7
Classifier: Programming Language :: Python :: 3.8
Classifier: Programming Language :: Python :: 3.9
Requires-Python: >=3.6, <4
License-File: LICENSE
License-File: NOTICE
License-File: AUTHORS.rst
Requires-Dist: boto3
Requires-Dist: smbprotocol
Requires-Dist: pathlib-mate (>=1.0.3)
Requires-Dist: smart-open (>=5.2.1)
Requires-Dist: boto-session-manager (>=0.0.2)
Requires-Dist: s3pathlib (>=1.0.10)
Requires-Dist: loguru (>=0.6.0)
Provides-Extra: tests
Requires-Dist: pytest ; extra == 'tests'
Requires-Dist: pytest-cov ; extra == 'tests'
